mcp_server_toolhouse/__init__.py
mcp_server_toolhouse/server.py
mcp_server_toolhouse-0.2.0.dist-info/METADATA
mcp_server_toolhouse-0.2.0.dist-info/WHEEL
mcp_server_toolhouse-0.2.0.dist-info/entry_points.txt
mcp_server_toolhouse-0.2.0.dist-info/licenses/LICENSE.md
mcp_server_toolhouse-0.2.0.dist-info/RECORD
